example_pkg/__init__.py
example_pkg/functions.py
functions/June7.py
functions/__init__.py
functions/functions.py
tealshwlibrary/June7.py
tealshwlibrary/June8.py
tealshwlibrary/__init__.py
tealshwlibrary-1.8.7.dist-info/LICENSE.txt
tealshwlibrary-1.8.7.dist-info/METADATA
tealshwlibrary-1.8.7.dist-info/WHEEL
tealshwlibrary-1.8.7.dist-info/top_level.txt
tealshwlibrary-1.8.7.dist-info/RECORD
