Metadata-Version: 2.1
Name: tealshwlibrary
Version: 1.8.7
Summary: testing how packages work
Home-page: https://github.com/Highfire1/teals_hw_library
Author: Anderson T
Author-email: 786954@learn.vsb.bc.ca
License: UNKNOWN
Project-URL: Bug Tracker, https://github.com/Highfire1/teals_hw_library/issues
Platform: UNKNOWN
Classifier: Programming Language :: Python :: 3
Classifier: License :: OSI Approved :: MIT License
Classifier: Operating System :: OS Independent
Requires-Python: >=3.6
